<?xml version="1.0" encoding="UTF-8"?>
<!DOCTYPE wallpapers SYSTEM "mate-wp-list.dtd">
<wallpapers>
    <wallpaper deleted="false">
        <name>Fedora 42 Time of Day</name>
        <filename>/usr/share/backgrounds/f42/default/f42.xml</filename>
        <options>zoom</options>
    </wallpaper>

    <wallpaper deleted="false">
        <name>Fedora 42 Day Default</name>
        <filename>/usr/share/backgrounds/f42/default/f42-01-day.jxl</filename>
        <options>zoom</options>
        <shade_type>solid</shade_type>
        <pcolor>#3c6eb4</pcolor>
        <scolor>#294172</scolor>
    </wallpaper>

    <wallpaper deleted="false">
        <name>Fedora 42 Night</name>
        <filename>/usr/share/backgrounds/f42/default/f42-01-night.jxl</filename>
        <options>zoom</options>
        <shade_type>solid</shade_type>
        <pcolor>#3c6eb4</pcolor>
        <scolor>#294172</scolor>
    </wallpaper>
</wallpapers>
